LICENSE
MANIFEST.in
README.rst
requirements.txt
setup.py
docker_scripts/__init__.py
docker_scripts/cli.py
docker_scripts/errors.py
docker_scripts/layers.py
docker_scripts/squash.py
docker_scripts/version.py
docker_scripts.egg-info/PKG-INFO
docker_scripts.egg-info/SOURCES.txt
docker_scripts.egg-info/dependency_links.txt
docker_scripts.egg-info/entry_points.txt
docker_scripts.egg-info/pbr.json
docker_scripts.egg-info/requires.txt
docker_scripts.egg-info/top_level.txt
docker_scripts/lib/__init__.py
docker_scripts/lib/common.py
docker_scripts/lib/xtarfile.py