Metadata-Version: 1.1
Name: docker-scripts
Version: 0.4.3
Summary: A swiss-knife tool that could be useful for people working with Docker
Home-page: https://github.com/goldmann/docker-scripts
Author: Marek Goldmann
Author-email: marek.goldmann@gmail.com
License: MIT
Download-URL: https://github.com/goldmann/docker-scripts/archive/0.4.3.tar.gz
Keywords: docker
Platform: UNKNOWN
